synengine/__init__.py
synengine/engine/__init__.py
synengine/engine/synpusher_engine_interface.py
synengine/engine/unity/__init__.py
synengine/engine/unity/unity_pipe_syngar_assetbundle.py
synengine/engine/unity/unity_pipe_syngar_scene_integ.py
synengine/engine/unity/unity_pipe_syngar_unittest.py
synengine/engine/unity/unity_pipe_syngar_utils.py
synengine/syngar_app/__init__.py
synengine/syngar_app/resource.py
synengine/utils/__init__.py
synengine/utils/const_key.py
synengine/utils/env.py
synengine/utils/grpc_convert_utils.py
synengine/utils/hash.py
synengine/utils/singleton.py
synengine-0.1.14.dist-info/METADATA
synengine-0.1.14.dist-info/WHEEL
synengine-0.1.14.dist-info/top_level.txt
synengine-0.1.14.dist-info/RECORD
